LICENSE
MANIFEST.in
README.md
pyproject.toml
setup.py
ducktrack/__init__.py
ducktrack/base_classes.py
ducktrack/elements.py
ducktrack/line.py
ducktrack/mathlibs.py
ducktrack/particles.py
ducktrack/temp_pyparticles.py
ducktrack/be_beamfields/BB6D.py
ducktrack/be_beamfields/BB6Ddata.py
ducktrack/be_beamfields/__init__.py
ducktrack/be_beamfields/beambeam.py
ducktrack/be_beamfields/boost.py
ducktrack/be_beamfields/gaussian_fields.py
ducktrack/be_beamfields/propagate_sigma_matrix.py
ducktrack/be_beamfields/qgauss.py
ducktrack/be_beamfields/slicing.py
ducktrack/be_beamfields/spacecharge.py
tests/test_acceleration.py
tests/test_acdipole.py
tests/test_acdipole_twiss.py
tests/test_amplitude_detuning.py
tests/test_aperture_polygon.py
tests/test_aperture_table.py
tests/test_aperture_turn_ele_and_monitor.py
tests/test_apertures.py
tests/test_attr_replicas_and_slices.py
tests/test_boris_spatial.py
tests/test_bucket_with_ref_energy_change.py
tests/test_cavity_absolute_time.py
tests/test_cavity_harmonic.py
tests/test_chromatic_functions_vs_madx.py
tests/test_coasting.py
tests/test_collective_tracker.py
tests/test_collimation.py
tests/test_coupling_edwards_teng.py
tests/test_electron_cooler.py
tests/test_element_characterization_functions.py
tests/test_element_internal_record.py
tests/test_elements.py
tests/test_elements_classflags.py
tests/test_elements_thick.py
tests/test_environment.py
tests/test_fcc_ee_solenoid_correction.py
tests/test_fcc_ee_solenoid_correction_new_optimize_api.py
tests/test_footprint.py
tests/test_freeze_longitudinal.py
tests/test_full_rings.py
tests/test_h6_sps_beamline.py
tests/test_hvkick.py
tests/test_ions.py
tests/test_json.py
tests/test_lhc_env.py
tests/test_lhc_match_phase_15.py
tests/test_line.py
tests/test_load.py
tests/test_load_vars.py
tests/test_lumi.py
tests/test_mad_writer.py
tests/test_madloader.py
tests/test_madnginterface.py
tests/test_magnet.py
tests/test_match_and_track_from_element.py
tests/test_match_coupling_knob.py
xtrack.egg-info/PKG-INFO
xtrack.egg-info/SOURCES.txt
xtrack.egg-info/dependency_links.txt
xtrack.egg-info/entry_points.txt
xtrack.egg-info/requires.txt
xtrack.egg-info/top_level.txt
