Metadata-Version: 2.4
Name: xtrack
Version: 0.98.14
Summary: Tracking library for particle accelerators
Author: G. Iadarola et al.
License-Expression: Apache-2.0
Project-URL: Homepage, https://xsuite.readthedocs.io/
Project-URL: Bug Tracker, https://github.com/xsuite/xsuite/issues
Project-URL: Documentation, https://xsuite.readthedocs.io/
Project-URL: Source Code, https://github.com/xsuite/xtrack
Project-URL: Download, https://pypi.python.org/pypi/xtrack
Requires-Python: >=3.9
License-File: LICENSE
Requires-Dist: numpy>=1.0
Requires-Dist: pandas>=2.0
Requires-Dist: scipy
Requires-Dist: tqdm
Requires-Dist: requests
Requires-Dist: xobjects
Requires-Dist: xdeps
Provides-Extra: tests
Requires-Dist: cpymad; extra == "tests"
Requires-Dist: nafflib; extra == "tests"
Requires-Dist: PyHEADTAIL; extra == "tests"
Requires-Dist: pytest; extra == "tests"
Requires-Dist: pytest-mock; extra == "tests"
Requires-Dist: pymadng==0.8.1; extra == "tests"
Requires-Dist: requests-mock; extra == "tests"
Requires-Dist: tfs-pandas; extra == "tests"
Provides-Extra: notebooks
Requires-Dist: jupyter; extra == "notebooks"
Requires-Dist: ipympl; extra == "notebooks"
Requires-Dist: xplt; extra == "notebooks"
Dynamic: license-file
